witheppy/__init__.py
witheppy/iddcurrent.py
witheppy/iddv800.py
witheppy/iddv960.py
witheppy/runandget.py
witheppy/runner.py
witheppy/eppyhelpers/__init__.py
witheppy/eppyhelpers/extfields.py
witheppy/eppyhelpers/geometry.py
witheppy/eppyhelpers/hvac.py
witheppy/eppyhelpers/iddhelpers.py
witheppy-0.1.8.dist-info/AUTHORS.rst
witheppy-0.1.8.dist-info/LICENSE
witheppy-0.1.8.dist-info/METADATA
witheppy-0.1.8.dist-info/WHEEL
witheppy-0.1.8.dist-info/top_level.txt
witheppy-0.1.8.dist-info/RECORD
