Metadata-Version: 2.1
Name: witheppy
Version: 0.1.8
Summary: Python packages built using eppy
Home-page: https://github.com/pyenergyplus/witheppy
Author: Santosh Philip
Author-email: santosh@noemail.com
License: MIT license
Keywords: witheppy
Platform: UNKNOWN
Classifier: Development Status :: 2 - Pre-Alpha
Classifier: Intended Audience :: Developers
Classifier: License :: OSI Approved :: MIT License
Classifier: Natural Language :: English
Classifier: Programming Language :: Python :: 3.5
Classifier: Programming Language :: Python :: 3.6
Classifier: Programming Language :: Python :: 3.7
Requires-Dist: eppy
